vsl_ial/__init__.py
vsl_ial/image_metric.py
vsl_ial/stress.py
vsl_ial/cs/__init__.py
vsl_ial/cs/cam.py
vsl_ial/cs/cielab.py
vsl_ial/cs/cieluv.py
vsl_ial/cs/ciexyy.py
vsl_ial/cs/hls.py
vsl_ial/cs/hsv.py
vsl_ial/cs/icacb.py
vsl_ial/cs/ictcp.py
vsl_ial/cs/jzazbz.py
vsl_ial/cs/linrgb.py
vsl_ial/cs/lms.py
vsl_ial/cs/oklab.py
vsl_ial/cs/opponent.py
vsl_ial/cs/pcs23.py
vsl_ial/cs/prolab.py
vsl_ial/cs/srgb.py
vsl_ial/cs/xyz.py
vsl_ial/datasets/illuminants.json
vsl_ial/datasets/load.py
vsl_ial/datasets/distance/__init__.py
vsl_ial/datasets/distance/combvd/leeds.json
vsl_ial/datasets/distance/combvd/rit-dupont.json
vsl_ial/datasets/distance/combvd/witt.json
vsl_ial/datasets/distance/combvd/bfd_p/bfd-c.json
vsl_ial/datasets/distance/combvd/bfd_p/bfd-d65.json
vsl_ial/datasets/distance/combvd/bfd_p/bfd-m.json
vsl_ial/datasets/distance/constant_hue/ebner_fairchild.json
vsl_ial/datasets/distance/constant_hue/hung_berns.json
vsl_ial/datasets/distance/constant_hue/xiao_averages.json
vsl_ial/datasets/distance/ellipses/macadam_1942.json
vsl_ial/datasets/distance/ellipses/macadam_1974.json
vsl_ial/datasets/distance/order/mrr-revised/munsell_2-0.csv
vsl_ial/datasets/distance/order/mrr-revised/munsell_3-0.csv
vsl_ial/datasets/distance/order/mrr-revised/munsell_3-1-0.csv
vsl_ial/datasets/distance/order/mrr-revised/munsell_3-1-1.csv
vsl_ial/datasets/distance/order/mrr-revised/munsell_3-2.csv
vsl_ial/datasets/distance/order/mrr-revised/munsell_3-3.csv
vsl_ial/datasets/sensitivities/__init__.py
vsl_ial/datasets/sensitivities/cie-1931-2.json
vsl_ial/datasets/sensitivities/cie-1964-10.json
vsl_ial/datasets/stash/fairchild_chen.json
vsl_ial/datasets/stash/luo-rigg.json
vsl_ial/eval/__main__.py
vsl_ial/eval/_base.py
vsl_ial/eval/cs.py
vsl_ial/eval/dataset.py
vsl_ial/eval/eval.py
vsl_ial/eval/metrics.py
vsl_ial/eval/pcs23-ucs-article.json
vsl_ial/image_appearance_model/__init__.py
vsl_ial/image_appearance_model/icam06.py
vsl_ial-0.0.10.dist-info/licenses/LICENSE
vsl_ial-0.0.10.dist-info/METADATA
vsl_ial-0.0.10.dist-info/WHEEL
vsl_ial-0.0.10.dist-info/top_level.txt
vsl_ial-0.0.10.dist-info/RECORD
