Metadata-Version: 2.4
Name: vsl_ial
Version: 0.0.10
Summary: Color spaces made reasonable
Author: Dmitry Nikolaev, Olga Basova, Valerii Timofeev
Author-email: Arseniy Terekhin <senyai@gmail.com>
License-Expression: MIT
Project-URL: Homepage, https://github.com/iitpvisionlab/vls_ial
Project-URL: Bug Reports, https://github.com/iitpvisionlab/vls_ial/issues
Project-URL: Source, https://github.com/iitpvisionlab/vls_ial
Classifier: Programming Language :: Python :: 3
Classifier: Operating System :: OS Independent
Requires-Python: >=3.10
License-File: LICENSE
Requires-Dist: numpy
Provides-Extra: extra
Requires-Dist: rich; extra == "extra"
Requires-Dist: json5; extra == "extra"
Requires-Dist: pydantic; extra == "extra"
Dynamic: license-file
